{
  "version": 6,
  "cmakeMinimumRequired": {
    "major": 3,
    "minor": 21,
    "patch": 0
  },
  "configurePresets": [
    {
      "name": "windows-msvc-debug",
      "displayName": "Windows MSVC Debug",
      "generator": "Ninja",
      "binaryDir": "${sourceDir}/build/windows-msvc-debug",
      "cacheVariables": {
        "CMAKE_BUILD_TYPE": "Debug",
        "CMAKE_TOOLCHAIN_FILE": "$env{VCPKG_ROOT}/scripts/buildsystems/vcpkg.cmake"
      },
      "condition": {
        "type": "equals",
        "lhs": "${hostSystemName}",
        "rhs": "Windows"
      }
    },
    {
      "name": "windows-msvc-release",
      "displayName": "Windows MSVC Release",
      "inherits": "windows-msvc-debug",
      "binaryDir": "${sourceDir}/build/windows-msvc-release",
      "cacheVariables": {
        "CMAKE_BUILD_TYPE": "Release"
      }
    },
    {
      "name": "windows-vs2026-qt-local",
      "displayName": "Windows VS 2026 with local Qt",
      "generator": "Visual Studio 18 2026",
      "architecture": "x64",
      "binaryDir": "${sourceDir}/build/vs2026",
      "cacheVariables": {
        "CMAKE_PREFIX_PATH": "I:/Qt/6.10.2/msvc2022_64"
      },
      "condition": {
        "type": "equals",
        "lhs": "${hostSystemName}",
        "rhs": "Windows"
      }
    }
  ],
  "buildPresets": [
    {
      "name": "windows-msvc-debug",
      "configurePreset": "windows-msvc-debug"
    },
    {
      "name": "windows-msvc-release",
      "configurePreset": "windows-msvc-release"
    },
    {
      "name": "windows-vs2026-qt-local-release",
      "configurePreset": "windows-vs2026-qt-local",
      "configuration": "Release"
    }
  ],
  "testPresets": [
    {
      "name": "windows-msvc-debug",
      "configurePreset": "windows-msvc-debug",
      "output": {
        "outputOnFailure": true
      }
    },
    {
      "name": "windows-vs2026-qt-local-release",
      "configurePreset": "windows-vs2026-qt-local",
      "configuration": "Release",
      "output": {
        "outputOnFailure": true
      }
    }
  ]
}
